{"trial_id": "9d18473195303d70489301e17731fab1", "hyperparameters": {"space": [{"class_name": "Int", "config": {"name": "units", "default": null, "conditions": [], "min_value": 32, "max_value": 512, "step": 32, "sampling": null}}, {"class_name": "Choice", "config": {"name": "learning_rate", "default": 0.01, "conditions": [], "values": [0.01, 0.001, 0.0001], "ordered": true}}], "values": {"units": 96, "learning_rate": 0.01, "tuner/epochs": 2, "tuner/initial_epoch": 0, "tuner/bracket": 4, "tuner/round": 0}}, "metrics": {"metrics": {"loss": {"direction": "min", "observations": [{"value": [85.44281768798828], "step": 0}]}, "mean_absolute_error": {"direction": "min", "observations": [{"value": [85.9403076171875], "step": 0}]}, "val_loss": {"direction": "min", "observations": [{"value": [80.97270965576172], "step": 0}]}, "val_mean_absolute_error": {"direction": "min", "observations": [{"value": [81.46926879882812], "step": 0}]}}}, "score": 80.97270965576172, "best_step": 0, "status": "COMPLETED"}